data/External_File_Info.txt
data/External_Time_Info.txt
data/FileSeries_Info.txt
data/img1/img-00610.png
data/img1/img-00611.png
data/img1/img-00612.png
data/img1/img-00613.png
data/img1/img-00614.png
data/img1/img-00615.png
data/img1/img-00616.png
data/img1/img-00617.png
data/img1/img-00618.png
data/img1/img-00619.png
data/img1/img-00620.png
data/img2/arbitrary_file.txt
data/img2/img-00625.png
data/img2/img-00626.png
data/img2/img-00627.png
data/img2/img-00628.png
data/img2/img-00629.png
data/img2/img-00630.png
data/img2/img-00631.png
data/img2/img-00632.png
data/img2/img-00633.png
data/isotherm/Spectro_WLI.tsv
data/isotherm/ValvePID_Pressure_resampled.tsv
filo/__init__.py
filo/analysis.py
filo/data_series.py
filo/file_series.py
filo/fileio.py
filo/formatters.py
filo/misc.py
filo/multiprocess.py
filo/parameters.py
filo/readers.py
filo/resample.py
filo/results.py
filo/viewers.py
filo-2.2.0.dist-info/licenses/LICENSE
tests/test_filo.py
filo-2.2.0.dist-info/METADATA
filo-2.2.0.dist-info/WHEEL
filo-2.2.0.dist-info/top_level.txt
filo-2.2.0.dist-info/RECORD
