Metadata-Version: 2.4
Name: filo
Version: 2.2.0
Summary: Managing files and file series
Author-email: Olivier Vincent <ovinc.py@gmail.com>
License: BSD 3-Clause License
Project-URL: Homepage, https://github.com/ovinc/filo
Project-URL: Documentation, https://github.com/ovinc/filo/README.md
Project-URL: Repository, https://github.com/ovinc/filo.git
Keywords: files,management,file,series
Classifier: Programming Language :: Python :: 3
Classifier: Operating System :: OS Independent
Classifier: License :: OSI Approved :: BSD License
Requires-Python: >=3.6
License-File: LICENSE
Requires-Dist: importlib-metadata
Requires-Dist: pandas
Requires-Dist: matplotlib
Dynamic: license-file
